adminlte3/__init__.py
adminlte3/admin.py
adminlte3/apps.py
adminlte3/compat.py
adminlte3/models.py
adminlte3/tests.py
adminlte3/views.py
adminlte3/migrations/__init__.py
adminlte3/templatetags/__init__.py
adminlte3/templatetags/adminlte_helpers.py
adminlte3_theme/__init__.py
adminlte3_theme/admin.py
adminlte3_theme/apps.py
adminlte3_theme/models.py
adminlte3_theme/tests.py
adminlte3_theme/views.py
adminlte3_theme/migrations/__init__.py
adminlte3_theme/templatetags/__init__.py
adminlte3_theme/templatetags/admin_menu.py
django_adminlte3/__init__.py
django_adminlte3/asgi.py
django_adminlte3/settings.py
django_adminlte3/urls.py
django_adminlte3/wsgi.py
django_adminlte3-0.0.1.dist-info/LICENCE
django_adminlte3-0.0.1.dist-info/METADATA
django_adminlte3-0.0.1.dist-info/WHEEL
django_adminlte3-0.0.1.dist-info/top_level.txt
django_adminlte3-0.0.1.dist-info/RECORD
